<?xml version="1.0" encoding="UTF-8"?>
<MMDModel>
    <globalSettings>
        <fileType>PMX</fileType>
        <fileVersion>2.000000</fileVersion>
        <modelNameJp>サン・マルコ広場</modelNameJp>
        <modelNameEn></modelNameEn>
        <commentJp>MMDステージデータ&#xD;&#xA;【サン・マルコ広場&#x20;Ver1.00】&#xD;&#xA;&#xD;&#xA;※透過パーツも忘れずに読み込んで下さい※&#xD;&#xA;&#xD;&#xA;スキアヴォーニ河岸ステージと繋げて&#xD;&#xA;使用することもできます。&#xD;&#xA;（センターボーンにX：-2810　Z：-270と入力）&#xD;&#xA;-------------------------------------&#xD;&#xA;制作：シロ</commentJp>
        <commentEn></commentEn>
        <numVertex>189897</numVertex>
        <numIndex>442713</numIndex>
        <vertexScale>8.000000</vertexScale>
        <importScale>0.010000</importScale>
    </globalSettings>
    <textureList>
        <Texture>
            <fileName>tex/ground.png</fileName>
        </Texture>
        <Texture>
            <fileName>tex/paving1.png</fileName>
        </Texture>
        <Texture>
            <fileName>tex/paving3.png</fileName>
        </Texture>
        <Texture>
            <fileName>tex/paving4.png</fileName>
        </Texture>
        <Texture>
            <fileName>tex/paving5.png</fileName>
        </Texture>
        <Texture>
            <fileName>tex/paving6.png</fileName>
        </Texture>
        <Texture>
            <fileName>tex/edge.png</fileName>
        </Texture>
        <Texture>
            <fileName>tex/line.png</fileName>
        </Texture>
        <Texture>
            <fileName>tex/bill_B.png</fileName>
        </Texture>
        <Texture>
            <fileName>tn01.bmp</fileName>
        </Texture>
        <Texture>
            <fileName>tex/meadow.png</fileName>
        </Texture>
        <Texture>
            <fileName>tex/sand.png</fileName>
        </Texture>
        <Texture>
            <fileName>tex/under1.png</fileName>
        </Texture>
        <Texture>
            <fileName>tex/bill_A.png</fileName>
        </Texture>
        <Texture>
            <fileName>tex/bill_C.png</fileName>
        </Texture>
        <Texture>
            <fileName>tex/bill_D.png</fileName>
        </Texture>
        <Texture>
            <fileName>tex/bill_E.png</fileName>
        </Texture>
        <Texture>
            <fileName>tex/c_block.png</fileName>
        </Texture>
        <Texture>
            <fileName>tex/paving2.png</fileName>
        </Texture>
        <Texture>
            <fileName>tex/roof_A.png</fileName>
        </Texture>
        <Texture>
            <fileName>tex/roof_B.png</fileName>
        </Texture>
        <Texture>
            <fileName>tex/roof_C.png</fileName>
        </Texture>
        <Texture>
            <fileName>tex/roof_D.png</fileName>
        </Texture>
        <Texture>
            <fileName>tex/roof_E.png</fileName>
        </Texture>
        <Texture>
            <fileName>tex/roof_F.png</fileName>
        </Texture>
        <Texture>
            <fileName>tex/old_wood.png</fileName>
        </Texture>
        <Texture>
            <fileName>tex/wallset_A.png</fileName>
        </Texture>
        <Texture>
            <fileName>tex/wallset_B.png</fileName>
        </Texture>
        <Texture>
            <fileName>tex/wallset_C.png</fileName>
        </Texture>
        <Texture>
            <fileName>tex/wallset_D.png</fileName>
        </Texture>
        <Texture>
            <fileName>met.sph</fileName>
        </Texture>
        <Texture>
            <fileName>tex/bill_vista.png</fileName>
        </Texture>
        <Texture>
            <fileName>tex/post.png</fileName>
        </Texture>
        <Texture>
            <fileName>tex/c_floor3.png</fileName>
        </Texture>
        <Texture>
            <fileName>tex/s_roof1.png</fileName>
        </Texture>
        <Texture>
            <fileName>tex/lamp.png</fileName>
        </Texture>
        <Texture>
            <fileName>li.spa</fileName>
        </Texture>
        <Texture>
            <fileName>tex/alpha.png</fileName>
        </Texture>
        <Texture>
            <fileName>tex/alpha3.png</fileName>
        </Texture>
        <Texture>
            <fileName>toon0.bmp</fileName>
        </Texture>
        <Texture>
            <fileName>toon01.bmp</fileName>
        </Texture>
        <Texture>
            <fileName>toon02.bmp</fileName>
        </Texture>
        <Texture>
            <fileName>toon03.bmp</fileName>
        </Texture>
        <Texture>
            <fileName>toon04.bmp</fileName>
        </Texture>
        <Texture>
            <fileName>toon05.bmp</fileName>
        </Texture>
        <Texture>
            <fileName>toon06.bmp</fileName>
        </Texture>
        <Texture>
            <fileName>toon07.bmp</fileName>
        </Texture>
        <Texture>
            <fileName>toon08.bmp</fileName>
        </Texture>
        <Texture>
            <fileName>toon09.bmp</fileName>
        </Texture>
        <Texture>
            <fileName>toon10.bmp</fileName>
        </Texture>
    </textureList>
    <materialList>
        <Material>
            <nameJp>海底</nameJp>
            <nameEn></nameEn>
            <materialName>0.kaitei</materialName>
            <translatedName>kaitei</translatedName>
            <surfaceName>0.kaitei</surfaceName>
            <diffuse>
                <r>0.900000</r>
                <g>0.900000</g>
                <b>0.900000</b>
                <a>1.000000</a>
            </diffuse>
            <specular>
                <r>0.030000</r>
                <g>0.030000</g>
                <b>0.030000</b>
            </specular>
            <shiness>6.000000</shiness>
            <ambient>
                <r>0.500000</r>
                <g>0.500000</g>
                <b>0.500000</b>
            </ambient>
            <sphereMode>None</sphereMode>
            <toonID>1</toonID>
            <edgeColor>
                <r>0.000000</r>
                <g>0.000000</g>
                <b>0.000000</b>
                <a>1.000000</a>
            </edgeColor>
            <edgeSize>2.000000</edgeSize>
            <textureID>0</textureID>
            <additionalTextureID>-1</additionalTextureID>
            <toonTextureID>-1</toonTextureID>
            <flags>8</flags>
            <isDrawBothFaces>0</isDrawBothFaces>
            <isDrawGroundShadow>0</isDrawGroundShadow>
            <isDrawSelfShadowMap>0</isDrawSelfShadowMap>
            <isDrawSelfShadow>1</isDrawSelfShadow>
            <isDrawEdge>0</isDrawEdge>
            <numIndex>72</numIndex>
        </Material>
        <Material>
            <nameJp>石畳Ａ</nameJp>
            <nameEn></nameEn>
            <materialName>1.ishidatamiA</materialName>
            <translatedName>ishidatamiA</translatedName>
            <surfaceName>1.ishidatamiA</surfaceName>
            <diffuse>
                <r>0.900000</r>
                <g>0.900000</g>
                <b>0.900000</b>
                <a>1.000000</a>
            </diffuse>
            <specular>
                <r>0.100000</r>
                <g>0.100000</g>
                <b>0.100000</b>
            </specular>
            <shiness>5.000000</shiness>
            <ambient>
                <r>0.500000</r>
                <g>0.500000</g>
                <b>0.500000</b>
            </ambient>
            <sphereMode>None</sphereMode>
            <toonID>1</toonID>
            <edgeColor>
                <r>0.000000</r>
                <g>0.000000</g>
                <b>0.000000</b>
                <a>1.000000</a>
            </edgeColor>
            <edgeSize>2.000000</edgeSize>
            <textureID>1</textureID>
            <additionalTextureID>-1</additionalTextureID>
            <toonTextureID>-1</toonTextureID>
            <flags>8</flags>
            <isDrawBothFaces>0</isDrawBothFaces>
            <isDrawGroundShadow>0</isDrawGroundShadow>
            <isDrawSelfShadowMap>0</isDrawSelfShadowMap>
            <isDrawSelfShadow>1</isDrawSelfShadow>
            <isDrawEdge>0</isDrawEdge>
            <numIndex>78</numIndex>
        </Material>
        <Material>
            <nameJp>石畳Ｂ</nameJp>
            <nameEn></nameEn>
            <materialName>2.ishidatamiB</materialName>
            <translatedName>ishidatamiB</translatedName>
            <surfaceName>2.ishidatamiB</surfaceName>
            <diffuse>
                <r>0.900000</r>
                <g>0.900000</g>
                <b>0.900000</b>
                <a>1.000000</a>
            </diffuse>
            <specular>
                <r>0.100000</r>
                <g>0.100000</g>
                <b>0.100000</b>
            </specular>
            <shiness>5.000000</shiness>
            <ambient>
                <r>0.500000</r>
                <g>0.500000</g>
                <b>0.500000</b>
            </ambient>
            <sphereMode>None</sphereMode>
            <toonID>1</toonID>
            <edgeColor>
                <r>0.000000</r>
                <g>0.000000</g>
                <b>0.000000</b>
                <a>1.000000</a>
            </edgeColor>
            <edgeSize>2.000000</edgeSize>
            <textureID>2</textureID>
            <additionalTextureID>-1</additionalTextureID>
            <toonTextureID>-1</toonTextureID>
            <flags>8</flags>
            <isDrawBothFaces>0</isDrawBothFaces>
            <isDrawGroundShadow>0</isDrawGroundShadow>
            <isDrawSelfShadowMap>0</isDrawSelfShadowMap>
            <isDrawSelfShadow>1</isDrawSelfShadow>
            <isDrawEdge>0</isDrawEdge>
            <numIndex>792</numIndex>
        </Material>
        <Material>
            <nameJp>石畳Ｃ</nameJp>
            <nameEn></nameEn>
            <materialName>3.ishidatamiC</materialName>
            <translatedName>ishidatamiC</translatedName>
            <surfaceName>3.ishidatamiC</surfaceName>
            <diffuse>
                <r>0.900000</r>
                <g>0.900000</g>
                <b>0.900000</b>
                <a>1.000000</a>
            </diffuse>
            <specular>
                <r>0.100000</r>
                <g>0.100000</g>
                <b>0.100000</b>
            </specular>
            <shiness>5.000000</shiness>
            <ambient>
                <r>0.500000</r>
                <g>0.500000</g>
                <b>0.500000</b>
            </ambient>
            <sphereMode>None</sphereMode>
            <toonID>1</toonID>
            <edgeColor>
                <r>0.000000</r>
                <g>0.000000</g>
                <b>0.000000</b>
                <a>1.000000</a>
            </edgeColor>
            <edgeSize>2.000000</edgeSize>
            <textureID>3</textureID>
            <additionalTextureID>-1</additionalTextureID>
            <toonTextureID>-1</toonTextureID>
            <flags>8</flags>
            <isDrawBothFaces>0</isDrawBothFaces>
            <isDrawGroundShadow>0</isDrawGroundShadow>
            <isDrawSelfShadowMap>0</isDrawSelfShadowMap>
            <isDrawSelfShadow>1</isDrawSelfShadow>
            <isDrawEdge>0</isDrawEdge>
            <numIndex>372</numIndex>
        </Material>
        <Material>
            <nameJp>石畳Ｄ</nameJp>
            <nameEn></nameEn>
            <materialName>4.ishidatamiE</materialName>
            <translatedName>ishidatamiE</translatedName>
            <surfaceName>4.ishidatamiE</surfaceName>
            <diffuse>
                <r>0.900000</r>
                <g>0.900000</g>
                <b>0.900000</b>
                <a>1.000000</a>
            </diffuse>
            <specular>
                <r>0.100000</r>
                <g>0.100000</g>
                <b>0.100000</b>
            </specular>
            <shiness>5.000000</shiness>
            <ambient>
                <r>0.500000</r>
                <g>0.500000</g>
                <b>0.500000</b>
            </ambient>
            <sphereMode>None</sphereMode>
            <toonID>1</toonID>
            <edgeColor>
                <r>0.000000</r>
                <g>0.000000</g>
                <b>0.000000</b>
                <a>1.000000</a>
            </edgeColor>
            <edgeSize>2.000000</edgeSize>
            <textureID>4</textureID>
            <additionalTextureID>-1</additionalTextureID>
            <toonTextureID>-1</toonTextureID>
            <flags>8</flags>
            <isDrawBothFaces>0</isDrawBothFaces>
            <isDrawGroundShadow>0</isDrawGroundShadow>
            <isDrawSelfShadowMap>0</isDrawSelfShadowMap>
            <isDrawSelfShadow>1</isDrawSelfShadow>
            <isDrawEdge>0</isDrawEdge>
            <numIndex>84</numIndex>
        </Material>
        <Material>
            <nameJp>石畳Ｅ</nameJp>
            <nameEn></nameEn>
            <materialName>5.ishidatamiE</materialName>
            <translatedName>ishidatamiE</translatedName>
            <surfaceName>5.ishidatamiE</surfaceName>
            <diffuse>
                <r>0.900000</r>
                <g>0.900000</g>
                <b>0.900000</b>
                <a>1.000000</a>
            </diffuse>
            <specular>
                <r>0.100000</r>
                <g>0.100000</g>
                <b>0.100000</b>
            </specular>
            <shiness>5.000000</shiness>
            <ambient>
                <r>0.500000</r>
                <g>0.500000</g>
                <b>0.500000</b>
            </ambient>
            <sphereMode>None</sphereMode>
            <toonID>1</toonID>
            <edgeColor>
                <r>0.000000</r>
                <g>0.000000</g>
                <b>0.000000</b>
                <a>1.000000</a>
            </edgeColor>
            <edgeSize>2.000000</edgeSize>
            <textureID>5</textureID>
            <additionalTextureID>-1</additionalTextureID>
            <toonTextureID>-1</toonTextureID>
            <flags>8</flags>
            <isDrawBothFaces>0</isDrawBothFaces>
            <isDrawGroundShadow>0</isDrawGroundShadow>
            <isDrawSelfShadowMap>0</isDrawSelfShadowMap>
            <isDrawSelfShadow>1</isDrawSelfShadow>
            <isDrawEdge>0</isDrawEdge>
            <numIndex>81</numIndex>
        </Material>
        <Material>
            <nameJp>縁</nameJp>
            <nameEn></nameEn>
            <materialName>6.en</materialName>
            <translatedName>en</translatedName>
            <surfaceName>6.en</surfaceName>
            <diffuse>
                <r>0.900000</r>
                <g>0.900000</g>
                <b>0.900000</b>
                <a>1.000000</a>
            </diffuse>
            <specular>
                <r>0.050000</r>
                <g>0.050000</g>
                <b>0.050000</b>
            </specular>
            <shiness>5.000000</shiness>
            <ambient>
                <r>0.500000</r>
                <g>0.500000</g>
                <b>0.500000</b>
            </ambient>
            <sphereMode>None</sphereMode>
            <toonID>1</toonID>
            <edgeColor>
                <r>0.000000</r>
                <g>0.000000</g>
                <b>0.000000</b>
                <a>1.000000</a>
            </edgeColor>
            <edgeSize>2.000000</edgeSize>
            <textureID>6</textureID>
            <additionalTextureID>-1</additionalTextureID>
            <toonTextureID>-1</toonTextureID>
            <flags>12</flags>
            <isDrawBothFaces>0</isDrawBothFaces>
            <isDrawGroundShadow>0</isDrawGroundShadow>
            <isDrawSelfShadowMap>1</isDrawSelfShadowMap>
            <isDrawSelfShadow>1</isDrawSelfShadow>
            <isDrawEdge>0</isDrawEdge>
            <numIndex>10710</numIndex>
        </Material>
        <Material>
            <nameJp>白線</nameJp>
            <nameEn></nameEn>
            <materialName>7.hakusen</materialName>
            <translatedName>hakusen</translatedName>
            <surfaceName>7.hakusen</surfaceName>
            <diffuse>
                <r>0.900000</r>
                <g>0.900000</g>
                <b>0.900000</b>
                <a>0.870000</a>
            </diffuse>
            <specular>
                <r>0.000000</r>
                <g>0.000000</g>
                <b>0.000000</b>
            </specular>
            <shiness>6.000000</shiness>
            <ambient>
                <r>0.500000</r>
                <g>0.500000</g>
                <b>0.500000</b>
            </ambient>
            <sphereMode>None</sphereMode>
            <toonID>1</toonID>
            <edgeColor>
                <r>0.000000</r>
                <g>0.000000</g>
                <b>0.000000</b>
                <a>1.000000</a>
            </edgeColor>
            <edgeSize>2.000000</edgeSize>
            <textureID>7</textureID>
            <additionalTextureID>-1</additionalTextureID>
            <toonTextureID>-1</toonTextureID>
            <flags>8</flags>
            <isDrawBothFaces>0</isDrawBothFaces>
            <isDrawGroundShadow>0</isDrawGroundShadow>
            <isDrawSelfShadowMap>0</isDrawSelfShadowMap>
            <isDrawSelfShadow>1</isDrawSelfShadow>
            <isDrawEdge>0</isDrawEdge>
            <numIndex>180</numIndex>
        </Material>
        <Material>
            <nameJp>井戸のフタ</nameJp>
            <nameEn></nameEn>
            <materialName>8.idonofuta</materialName>
            <translatedName>idonofuta</translatedName>
            <surfaceName>8.idonofuta</surfaceName>
            <diffuse>
                <r>0.900000</r>
                <g>0.900000</g>
                <b>0.900000</b>
                <a>1.000000</a>
            </diffuse>
            <specular>
                <r>0.050000</r>
                <g>0.050000</g>
                <b>0.050000</b>
            </specular>
            <shiness>5.000000</shiness>
            <ambient>
                <r>0.500000</r>
                <g>0.500000</g>
                <b>0.500000</b>
            </ambient>
            <sphereMode>None</sphereMode>
            <toonID>0</toonID>
            <edgeColor>
                <r>0.000000</r>
                <g>0.000000</g>
                <b>0.000000</b>
                <a>1.000000</a>
            </edgeColor>
            <edgeSize>2.000000</edgeSize>
            <textureID>8</textureID>
            <additionalTextureID>-1</additionalTextureID>
            <toonTextureID>9</toonTextureID>
            <flags>8</flags>
            <isDrawBothFaces>0</isDrawBothFaces>
            <isDrawGroundShadow>0</isDrawGroundShadow>
            <isDrawSelfShadowMap>0</isDrawSelfShadowMap>
            <isDrawSelfShadow>1</isDrawSelfShadow>
            <isDrawEdge>0</isDrawEdge>
            <numIndex>330</numIndex>
        </Material>
        <Material>
            <nameJp>草地</nameJp>
            <nameEn></nameEn>
            <materialName>9.kusachi</materialName>
            <translatedName>kusachi</translatedName>
            <surfaceName>9.kusachi</surfaceName>
            <diffuse>
                <r>0.900000</r>
                <g>0.900000</g>
                <b>0.900000</b>
                <a>1.000000</a>
            </diffuse>
            <specular>
                <r>0.100000</r>
                <g>0.100000</g>
                <b>0.100000</b>
            </specular>
            <shiness>5.000000</shiness>
            <ambient>
                <r>0.500000</r>
                <g>0.500000</g>
                <b>0.500000</b>
            </ambient>
            <sphereMode>None</sphereMode>
            <toonID>1</toonID>
            <edgeColor>
                <r>0.000000</r>
                <g>0.000000</g>
                <b>0.000000</b>
                <a>1.000000</a>
            </edgeColor>
            <edgeSize>2.000000</edgeSize>
            <textureID>10</textureID>
            <additionalTextureID>-1</additionalTextureID>
            <toonTextureID>-1</toonTextureID>
            <flags>8</flags>
            <isDrawBothFaces>0</isDrawBothFaces>
            <isDrawGroundShadow>0</isDrawGroundShadow>
            <isDrawSelfShadowMap>0</isDrawSelfShadowMap>
            <isDrawSelfShadow>1</isDrawSelfShadow>
            <isDrawEdge>0</isDrawEdge>
            <numIndex>360</numIndex>
        </Material>
        <Material>
            <nameJp>砂地</nameJp>
            <nameEn></nameEn>
            <materialName>10.sunaji</materialName>
            <translatedName>sunaji</translatedName>
            <surfaceName>10.sunaji</surfaceName>
            <diffuse>
                <r>0.900000</r>
                <g>0.900000</g>
                <b>0.900000</b>
                <a>1.000000</a>
            </diffuse>
            <specular>
                <r>0.100000</r>
                <g>0.100000</g>
                <b>0.100000</b>
            </specular>
            <shiness>5.000000</shiness>
            <ambient>
                <r>0.500000</r>
                <g>0.500000</g>
                <b>0.500000</b>
            </ambient>
            <sphereMode>None</sphereMode>
            <toonID>1</toonID>
            <edgeColor>
                <r>0.000000</r>
                <g>0.000000</g>
                <b>0.000000</b>
                <a>1.000000</a>
            </edgeColor>
            <edgeSize>2.000000</edgeSize>
            <textureID>11</textureID>
            <additionalTextureID>-1</additionalTextureID>
            <toonTextureID>-1</toonTextureID>
            <flags>8</flags>
            <isDrawBothFaces>0</isDrawBothFaces>
            <isDrawGroundShadow>0</isDrawGroundShadow>
            <isDrawSelfShadowMap>0</isDrawSelfShadowMap>
            <isDrawSelfShadow>1</isDrawSelfShadow>
            <isDrawEdge>0</isDrawEdge>
            <numIndex>87</numIndex>
        </Material>
        <Material>
            <nameJp>下壁</nameJp>
            <nameEn></nameEn>
            <materialName>11.shimokabe</materialName>
            <translatedName>shimokabe</translatedName>
            <surfaceName>11.shimokabe</surfaceName>
            <diffuse>
                <r>0.900000</r>
                <g>0.900000</g>
                <b>0.900000</b>
                <a>1.000000</a>
            </diffuse>
            <specular>
                <r>0.050000</r>
                <g>0.050000</g>
                <b>0.050000</b>
            </specular>
            <shiness>5.000000</shiness>
            <ambient>
                <r>0.500000</r>
                <g>0.500000</g>
                <b>0.500000</b>
            </ambient>
            <sphereMode>None</sphereMode>
            <toonID>1</toonID>
            <edgeColor>
                <r>0.000000</r>
                <g>0.000000</g>
                <b>0.000000</b>
                <a>1.000000</a>
            </edgeColor>
            <edgeSize>2.000000</edgeSize>
            <textureID>12</textureID>
            <additionalTextureID>-1</additionalTextureID>
            <toonTextureID>-1</toonTextureID>
            <flags>12</flags>
            <isDrawBothFaces>0</isDrawBothFaces>
            <isDrawGroundShadow>0</isDrawGroundShadow>
            <isDrawSelfShadowMap>1</isDrawSelfShadowMap>
            <isDrawSelfShadow>1</isDrawSelfShadow>
            <isDrawEdge>0</isDrawEdge>
            <numIndex>912</numIndex>
        </Material>
        <Material>
            <nameJp>建物Ａ</nameJp>
            <nameEn></nameEn>
            <materialName>12.tatemonoA</materialName>
            <translatedName>tatemonoA</translatedName>
            <surfaceName>12.tatemonoA</surfaceName>
            <diffuse>
                <r>0.900000</r>
                <g>0.900000</g>
                <b>0.900000</b>
                <a>1.000000</a>
            </diffuse>
            <specular>
                <r>0.050000</r>
                <g>0.050000</g>
                <b>0.050000</b>
            </specular>
            <shiness>5.000000</shiness>
            <ambient>
                <r>0.500000</r>
                <g>0.500000</g>
                <b>0.500000</b>
            </ambient>
            <sphereMode>None</sphereMode>
            <toonID>1</toonID>
            <edgeColor>
                <r>0.000000</r>
                <g>0.000000</g>
                <b>0.000000</b>
                <a>1.000000</a>
            </edgeColor>
            <edgeSize>2.000000</edgeSize>
            <textureID>13</textureID>
            <additionalTextureID>-1</additionalTextureID>
            <toonTextureID>-1</toonTextureID>
            <flags>12</flags>
            <isDrawBothFaces>0</isDrawBothFaces>
            <isDrawGroundShadow>0</isDrawGroundShadow>
            <isDrawSelfShadowMap>1</isDrawSelfShadowMap>
            <isDrawSelfShadow>1</isDrawSelfShadow>
            <isDrawEdge>0</isDrawEdge>
            <numIndex>37863</numIndex>
        </Material>
        <Material>
            <nameJp>建物Ｂ</nameJp>
            <nameEn></nameEn>
            <materialName>13.tatemonoB</materialName>
            <translatedName>tatemonoB</translatedName>
            <surfaceName>13.tatemonoB</surfaceName>
            <diffuse>
                <r>0.900000</r>
                <g>0.900000</g>
                <b>0.900000</b>
                <a>1.000000</a>
            </diffuse>
            <specular>
                <r>0.050000</r>
                <g>0.050000</g>
                <b>0.050000</b>
            </specular>
            <shiness>5.000000</shiness>
            <ambient>
                <r>0.500000</r>
                <g>0.500000</g>
                <b>0.500000</b>
            </ambient>
            <sphereMode>None</sphereMode>
            <toonID>1</toonID>
            <edgeColor>
                <r>0.000000</r>
                <g>0.000000</g>
                <b>0.000000</b>
                <a>1.000000</a>
            </edgeColor>
            <edgeSize>2.000000</edgeSize>
            <textureID>8</textureID>
            <additionalTextureID>-1</additionalTextureID>
            <toonTextureID>-1</toonTextureID>
            <flags>12</flags>
            <isDrawBothFaces>0</isDrawBothFaces>
            <isDrawGroundShadow>0</isDrawGroundShadow>
            <isDrawSelfShadowMap>1</isDrawSelfShadowMap>
            <isDrawSelfShadow>1</isDrawSelfShadow>
            <isDrawEdge>0</isDrawEdge>
            <numIndex>7026</numIndex>
        </Material>
        <Material>
            <nameJp>建物Ｃ</nameJp>
            <nameEn></nameEn>
            <materialName>14.tatemonoC</materialName>
            <translatedName>tatemonoC</translatedName>
            <surfaceName>14.tatemonoC</surfaceName>
            <diffuse>
                <r>0.900000</r>
                <g>0.900000</g>
                <b>0.900000</b>
                <a>1.000000</a>
            </diffuse>
            <specular>
                <r>0.050000</r>
                <g>0.050000</g>
                <b>0.050000</b>
            </specular>
            <shiness>5.000000</shiness>
            <ambient>
                <r>0.500000</r>
                <g>0.500000</g>
                <b>0.500000</b>
            </ambient>
            <sphereMode>None</sphereMode>
            <toonID>1</toonID>
            <edgeColor>
                <r>0.000000</r>
                <g>0.000000</g>
                <b>0.000000</b>
                <a>1.000000</a>
            </edgeColor>
            <edgeSize>2.000000</edgeSize>
            <textureID>14</textureID>
            <additionalTextureID>-1</additionalTextureID>
            <toonTextureID>-1</toonTextureID>
            <flags>12</flags>
            <isDrawBothFaces>0</isDrawBothFaces>
            <isDrawGroundShadow>0</isDrawGroundShadow>
            <isDrawSelfShadowMap>1</isDrawSelfShadowMap>
            <isDrawSelfShadow>1</isDrawSelfShadow>
            <isDrawEdge>0</isDrawEdge>
            <numIndex>540</numIndex>
        </Material>
        <Material>
            <nameJp>建物Ｄ</nameJp>
            <nameEn></nameEn>
            <materialName>15.tatemonoE</materialName>
            <translatedName>tatemonoE</translatedName>
            <surfaceName>15.tatemonoE</surfaceName>
            <diffuse>
                <r>0.900000</r>
                <g>0.900000</g>
                <b>0.900000</b>
                <a>1.000000</a>
            </diffuse>
            <specular>
                <r>0.050000</r>
                <g>0.050000</g>
                <b>0.050000</b>
            </specular>
            <shiness>5.000000</shiness>
            <ambient>
                <r>0.500000</r>
                <g>0.500000</g>
                <b>0.500000</b>
            </ambient>
            <sphereMode>None</sphereMode>
            <toonID>0</toonID>
            <edgeColor>
                <r>0.000000</r>
                <g>0.000000</g>
                <b>0.000000</b>
                <a>1.000000</a>
            </edgeColor>
            <edgeSize>2.000000</edgeSize>
            <textureID>15</textureID>
            <additionalTextureID>-1</additionalTextureID>
            <toonTextureID>9</toonTextureID>
            <flags>12</flags>
            <isDrawBothFaces>0</isDrawBothFaces>
            <isDrawGroundShadow>0</isDrawGroundShadow>
            <isDrawSelfShadowMap>1</isDrawSelfShadowMap>
            <isDrawSelfShadow>1</isDrawSelfShadow>
            <isDrawEdge>0</isDrawEdge>
            <numIndex>83649</numIndex>
        </Material>
        <Material>
            <nameJp>建物Ｅ</nameJp>
            <nameEn></nameEn>
            <materialName>16.tatemonoE</materialName>
            <translatedName>tatemonoE</translatedName>
            <surfaceName>16.tatemonoE</surfaceName>
            <diffuse>
                <r>0.900000</r>
                <g>0.900000</g>
                <b>0.900000</b>
                <a>1.000000</a>
            </diffuse>
            <specular>
                <r>0.050000</r>
                <g>0.050000</g>
                <b>0.050000</b>
            </specular>
            <shiness>5.000000</shiness>
            <ambient>
                <r>0.500000</r>
                <g>0.500000</g>
                <b>0.500000</b>
            </ambient>
            <sphereMode>None</sphereMode>
            <toonID>0</toonID>
            <edgeColor>
                <r>0.000000</r>
                <g>0.000000</g>
                <b>0.000000</b>
                <a>1.000000</a>
            </edgeColor>
            <edgeSize>2.000000</edgeSize>
            <textureID>16</textureID>
            <additionalTextureID>-1</additionalTextureID>
            <toonTextureID>9</toonTextureID>
            <flags>12</flags>
            <isDrawBothFaces>0</isDrawBothFaces>
            <isDrawGroundShadow>0</isDrawGroundShadow>
            <isDrawSelfShadowMap>1</isDrawSelfShadowMap>
            <isDrawSelfShadow>1</isDrawSelfShadow>
            <isDrawEdge>0</isDrawEdge>
            <numIndex>80496</numIndex>
        </Material>
        <Material>
            <nameJp>赤レンガ</nameJp>
            <nameEn></nameEn>
            <materialName>17.akarenga</materialName>
            <translatedName>akarenga</translatedName>
            <surfaceName>17.akarenga</surfaceName>
            <diffuse>
                <r>0.900000</r>
                <g>0.900000</g>
                <b>0.900000</b>
                <a>1.000000</a>
            </diffuse>
            <specular>
                <r>0.050000</r>
                <g>0.050000</g>
                <b>0.050000</b>
            </specular>
            <shiness>5.000000</shiness>
            <ambient>
                <r>0.500000</r>
                <g>0.500000</g>
                <b>0.500000</b>
            </ambient>
            <sphereMode>None</sphereMode>
            <toonID>1</toonID>
            <edgeColor>
                <r>0.000000</r>
                <g>0.000000</g>
                <b>0.000000</b>
                <a>1.000000</a>
            </edgeColor>
            <edgeSize>2.000000</edgeSize>
            <textureID>17</textureID>
            <additionalTextureID>-1</additionalTextureID>
            <toonTextureID>-1</toonTextureID>
            <flags>12</flags>
            <isDrawBothFaces>0</isDrawBothFaces>
            <isDrawGroundShadow>0</isDrawGroundShadow>
            <isDrawSelfShadowMap>1</isDrawSelfShadowMap>
            <isDrawSelfShadow>1</isDrawSelfShadow>
            <isDrawEdge>0</isDrawEdge>
            <numIndex>1239</numIndex>
        </Material>
        <Material>
            <nameJp>古レンガ</nameJp>
            <nameEn></nameEn>
            <materialName>18.korenga</materialName>
            <translatedName>korenga</translatedName>
            <surfaceName>18.korenga</surfaceName>
            <diffuse>
                <r>0.900000</r>
                <g>0.900000</g>
                <b>0.900000</b>
                <a>1.000000</a>
            </diffuse>
            <specular>
                <r>0.100000</r>
                <g>0.100000</g>
                <b>0.100000</b>
            </specular>
            <shiness>5.000000</shiness>
            <ambient>
                <r>0.500000</r>
                <g>0.500000</g>
                <b>0.500000</b>
            </ambient>
            <sphereMode>None</sphereMode>
            <toonID>1</toonID>
            <edgeColor>
                <r>0.000000</r>
                <g>0.000000</g>
                <b>0.000000</b>
                <a>1.000000</a>
            </edgeColor>
            <edgeSize>2.000000</edgeSize>
            <textureID>18</textureID>
            <additionalTextureID>-1</additionalTextureID>
            <toonTextureID>-1</toonTextureID>
            <flags>12</flags>
            <isDrawBothFaces>0</isDrawBothFaces>
            <isDrawGroundShadow>0</isDrawGroundShadow>
            <isDrawSelfShadowMap>1</isDrawSelfShadowMap>
            <isDrawSelfShadow>1</isDrawSelfShadow>
            <isDrawEdge>0</isDrawEdge>
            <numIndex>1188</numIndex>
        </Material>
        <Material>
            <nameJp>屋根Ａ</nameJp>
            <nameEn></nameEn>
            <materialName>19.yaneA</materialName>
            <translatedName>yaneA</translatedName>
            <surfaceName>19.yaneA</surfaceName>
            <diffuse>
                <r>0.900000</r>
                <g>0.900000</g>
                <b>0.900000</b>
                <a>1.000000</a>
            </diffuse>
            <specular>
                <r>0.050000</r>
                <g>0.050000</g>
                <b>0.050000</b>
            </specular>
            <shiness>5.000000</shiness>
            <ambient>
                <r>0.500000</r>
                <g>0.500000</g>
                <b>0.500000</b>
            </ambient>
            <sphereMode>None</sphereMode>
            <toonID>1</toonID>
            <edgeColor>
                <r>0.000000</r>
                <g>0.000000</g>
                <b>0.000000</b>
                <a>1.000000</a>
            </edgeColor>
            <edgeSize>2.000000</edgeSize>
            <textureID>19</textureID>
            <additionalTextureID>-1</additionalTextureID>
            <toonTextureID>-1</toonTextureID>
            <flags>12</flags>
            <isDrawBothFaces>0</isDrawBothFaces>
            <isDrawGroundShadow>0</isDrawGroundShadow>
            <isDrawSelfShadowMap>1</isDrawSelfShadowMap>
            <isDrawSelfShadow>1</isDrawSelfShadow>
            <isDrawEdge>0</isDrawEdge>
            <numIndex>1935</numIndex>
        </Material>
        <Material>
            <nameJp>屋根Ａ2</nameJp>
            <nameEn></nameEn>
            <materialName>20.yaneA2</materialName>
            <translatedName>yaneA2</translatedName>
            <surfaceName>20.yaneA2</surfaceName>
            <diffuse>
                <r>0.717647</r>
                <g>0.717647</g>
                <b>0.643137</b>
                <a>1.000000</a>
            </diffuse>
            <specular>
                <r>0.050000</r>
                <g>0.050000</g>
                <b>0.050000</b>
            </specular>
            <shiness>5.000000</shiness>
            <ambient>
                <r>0.384314</r>
                <g>0.380392</g>
                <b>0.301961</b>
            </ambient>
            <sphereMode>None</sphereMode>
            <toonID>1</toonID>
            <edgeColor>
                <r>0.000000</r>
                <g>0.000000</g>
                <b>0.000000</b>
                <a>1.000000</a>
            </edgeColor>
            <edgeSize>2.000000</edgeSize>
            <textureID>19</textureID>
            <additionalTextureID>-1</additionalTextureID>
            <toonTextureID>-1</toonTextureID>
            <flags>12</flags>
            <isDrawBothFaces>0</isDrawBothFaces>
            <isDrawGroundShadow>0</isDrawGroundShadow>
            <isDrawSelfShadowMap>1</isDrawSelfShadowMap>
            <isDrawSelfShadow>1</isDrawSelfShadow>
            <isDrawEdge>0</isDrawEdge>
            <numIndex>396</numIndex>
        </Material>
        <Material>
            <nameJp>屋根Ｂ</nameJp>
            <nameEn></nameEn>
            <materialName>21.yaneB</materialName>
            <translatedName>yaneB</translatedName>
            <surfaceName>21.yaneB</surfaceName>
            <diffuse>
                <r>0.900000</r>
                <g>0.900000</g>
                <b>0.900000</b>
                <a>1.000000</a>
            </diffuse>
            <specular>
                <r>0.050000</r>
                <g>0.050000</g>
                <b>0.050000</b>
            </specular>
            <shiness>5.000000</shiness>
            <ambient>
                <r>0.500000</r>
                <g>0.500000</g>
                <b>0.500000</b>
            </ambient>
            <sphereMode>None</sphereMode>
            <toonID>1</toonID>
            <edgeColor>
                <r>0.000000</r>
                <g>0.000000</g>
                <b>0.000000</b>
                <a>1.000000</a>
            </edgeColor>
            <edgeSize>2.000000</edgeSize>
            <textureID>20</textureID>
            <additionalTextureID>-1</additionalTextureID>
            <toonTextureID>-1</toonTextureID>
            <flags>12</flags>
            <isDrawBothFaces>0</isDrawBothFaces>
            <isDrawGroundShadow>0</isDrawGroundShadow>
            <isDrawSelfShadowMap>1</isDrawSelfShadowMap>
            <isDrawSelfShadow>1</isDrawSelfShadow>
            <isDrawEdge>0</isDrawEdge>
            <numIndex>309</numIndex>
        </Material>
        <Material>
            <nameJp>屋根Ｃ</nameJp>
            <nameEn></nameEn>
            <materialName>22.yaneC</materialName>
            <translatedName>yaneC</translatedName>
            <surfaceName>22.yaneC</surfaceName>
            <diffuse>
                <r>0.900000</r>
                <g>0.900000</g>
                <b>0.900000</b>
                <a>1.000000</a>
            </diffuse>
            <specular>
                <r>0.050000</r>
                <g>0.050000</g>
                <b>0.050000</b>
            </specular>
            <shiness>5.000000</shiness>
            <ambient>
                <r>0.500000</r>
                <g>0.500000</g>
                <b>0.500000</b>
            </ambient>
            <sphereMode>None</sphereMode>
            <toonID>1</toonID>
            <edgeColor>
                <r>0.000000</r>
                <g>0.000000</g>
                <b>0.000000</b>
                <a>1.000000</a>
            </edgeColor>
            <edgeSize>2.000000</edgeSize>
            <textureID>21</textureID>
            <additionalTextureID>-1</additionalTextureID>
            <toonTextureID>-1</toonTextureID>
            <flags>12</flags>
            <isDrawBothFaces>0</isDrawBothFaces>
            <isDrawGroundShadow>0</isDrawGroundShadow>
            <isDrawSelfShadowMap>1</isDrawSelfShadowMap>
            <isDrawSelfShadow>1</isDrawSelfShadow>
            <isDrawEdge>0</isDrawEdge>
            <numIndex>66</numIndex>
        </Material>
        <Material>
            <nameJp>屋根Ｄ</nameJp>
            <nameEn></nameEn>
            <materialName>23.yaneE</materialName>
            <translatedName>yaneE</translatedName>
            <surfaceName>23.yaneE</surfaceName>
            <diffuse>
                <r>0.900000</r>
                <g>0.900000</g>
                <b>0.900000</b>
                <a>1.000000</a>
            </diffuse>
            <specular>
                <r>0.050000</r>
                <g>0.050000</g>
                <b>0.050000</b>
            </specular>
            <shiness>5.000000</shiness>
            <ambient>
                <r>0.500000</r>
                <g>0.500000</g>
                <b>0.500000</b>
            </ambient>
            <sphereMode>None</sphereMode>
            <toonID>1</toonID>
            <edgeColor>
                <r>0.000000</r>
                <g>0.000000</g>
                <b>0.000000</b>
                <a>1.000000</a>
            </edgeColor>
            <edgeSize>2.000000</edgeSize>
            <textureID>22</textureID>
            <additionalTextureID>-1</additionalTextureID>
            <toonTextureID>-1</toonTextureID>
            <flags>12</flags>
            <isDrawBothFaces>0</isDrawBothFaces>
            <isDrawGroundShadow>0</isDrawGroundShadow>
            <isDrawSelfShadowMap>1</isDrawSelfShadowMap>
            <isDrawSelfShadow>1</isDrawSelfShadow>
            <isDrawEdge>0</isDrawEdge>
            <numIndex>252</numIndex>
        </Material>
        <Material>
            <nameJp>屋根Ｅ</nameJp>
            <nameEn></nameEn>
            <materialName>24.yaneE</materialName>
            <translatedName>yaneE</translatedName>
            <surfaceName>24.yaneE</surfaceName>
            <diffuse>
                <r>0.900000</r>
                <g>0.900000</g>
                <b>0.900000</b>
                <a>1.000000</a>
            </diffuse>
            <specular>
                <r>0.050000</r>
                <g>0.050000</g>
                <b>0.050000</b>
            </specular>
            <shiness>5.000000</shiness>
            <ambient>
                <r>0.500000</r>
                <g>0.500000</g>
                <b>0.500000</b>
            </ambient>
            <sphereMode>None</sphereMode>
            <toonID>1</toonID>
            <edgeColor>
                <r>0.000000</r>
                <g>0.000000</g>
                <b>0.000000</b>
                <a>1.000000</a>
            </edgeColor>
            <edgeSize>2.000000</edgeSize>
            <textureID>23</textureID>
            <additionalTextureID>-1</additionalTextureID>
            <toonTextureID>-1</toonTextureID>
            <flags>12</flags>
            <isDrawBothFaces>0</isDrawBothFaces>
            <isDrawGroundShadow>0</isDrawGroundShadow>
            <isDrawSelfShadowMap>1</isDrawSelfShadowMap>
            <isDrawSelfShadow>1</isDrawSelfShadow>
            <isDrawEdge>0</isDrawEdge>
            <numIndex>372</numIndex>
        </Material>
        <Material>
            <nameJp>屋根Ｆ</nameJp>
            <nameEn></nameEn>
            <materialName>25.yaneF</materialName>
            <translatedName>yaneF</translatedName>
            <surfaceName>25.yaneF</surfaceName>
            <diffuse>
                <r>0.900000</r>
                <g>0.900000</g>
                <b>0.900000</b>
                <a>1.000000</a>
            </diffuse>
            <specular>
                <r>0.050000</r>
                <g>0.050000</g>
                <b>0.050000</b>
            </specular>
            <shiness>5.000000</shiness>
            <ambient>
                <r>0.500000</r>
                <g>0.500000</g>
                <b>0.500000</b>
            </ambient>
            <sphereMode>None</sphereMode>
            <toonID>0</toonID>
            <edgeColor>
                <r>0.000000</r>
                <g>0.000000</g>
                <b>0.000000</b>
                <a>1.000000</a>
            </edgeColor>
            <edgeSize>2.000000</edgeSize>
            <textureID>24</textureID>
            <additionalTextureID>-1</additionalTextureID>
            <toonTextureID>9</toonTextureID>
            <flags>12</flags>
            <isDrawBothFaces>0</isDrawBothFaces>
            <isDrawGroundShadow>0</isDrawGroundShadow>
            <isDrawSelfShadowMap>1</isDrawSelfShadowMap>
            <isDrawSelfShadow>1</isDrawSelfShadow>
            <isDrawEdge>0</isDrawEdge>
            <numIndex>6768</numIndex>
        </Material>
        <Material>
            <nameJp>発光</nameJp>
            <nameEn></nameEn>
            <materialName>26.hakkou</materialName>
            <translatedName>hakkou</translatedName>
            <surfaceName>26.hakkou</surfaceName>
            <diffuse>
                <r>1.000000</r>
                <g>0.961000</g>
                <b>0.753000</b>
                <a>1.000000</a>
            </diffuse>
            <specular>
                <r>0.000000</r>
                <g>0.000000</g>
                <b>0.000000</b>
            </specular>
            <shiness>109.000000</shiness>
            <ambient>
                <r>1.000000</r>
                <g>0.961000</g>
                <b>0.753000</b>
            </ambient>
            <sphereMode>Multiply</sphereMode>
            <toonID>0</toonID>
            <edgeColor>
                <r>0.000000</r>
                <g>0.000000</g>
                <b>0.000000</b>
                <a>1.000000</a>
            </edgeColor>
            <edgeSize>2.000000</edgeSize>
            <textureID>-1</textureID>
            <additionalTextureID>-1</additionalTextureID>
            <toonTextureID>9</toonTextureID>
            <flags>12</flags>
            <isDrawBothFaces>0</isDrawBothFaces>
            <isDrawGroundShadow>0</isDrawGroundShadow>
            <isDrawSelfShadowMap>1</isDrawSelfShadowMap>
            <isDrawSelfShadow>1</isDrawSelfShadow>
            <isDrawEdge>0</isDrawEdge>
            <numIndex>5124</numIndex>
        </Material>
        <Material>
            <nameJp>板</nameJp>
            <nameEn></nameEn>
            <materialName>27.ita</materialName>
            <translatedName>ita</translatedName>
            <surfaceName>27.ita</surfaceName>
            <diffuse>
                <r>0.900000</r>
                <g>0.900000</g>
                <b>0.900000</b>
                <a>1.000000</a>
            </diffuse>
            <specular>
                <r>0.050000</r>
                <g>0.050000</g>
                <b>0.050000</b>
            </specular>
            <shiness>5.000000</shiness>
            <ambient>
                <r>0.500000</r>
                <g>0.500000</g>
                <b>0.500000</b>
            </ambient>
            <sphereMode>None</sphereMode>
            <toonID>1</toonID>
            <edgeColor>
                <r>0.000000</r>
                <g>0.000000</g>
                <b>0.000000</b>
                <a>1.000000</a>
            </edgeColor>
            <edgeSize>2.000000</edgeSize>
            <textureID>25</textureID>
            <additionalTextureID>-1</additionalTextureID>
            <toonTextureID>-1</toonTextureID>
            <flags>12</flags>
            <isDrawBothFaces>0</isDrawBothFaces>
            <isDrawGroundShadow>0</isDrawGroundShadow>
            <isDrawSelfShadowMap>1</isDrawSelfShadowMap>
            <isDrawSelfShadow>1</isDrawSelfShadow>
            <isDrawEdge>0</isDrawEdge>
            <numIndex>2088</numIndex>
        </Material>
        <Material>
            <nameJp>壁Ａ</nameJp>
            <nameEn></nameEn>
            <materialName>28.kabeA</materialName>
            <translatedName>kabeA</translatedName>
            <surfaceName>28.kabeA</surfaceName>
            <diffuse>
                <r>0.900000</r>
                <g>0.900000</g>
                <b>0.900000</b>
                <a>1.000000</a>
            </diffuse>
            <specular>
                <r>0.050000</r>
                <g>0.050000</g>
                <b>0.050000</b>
            </specular>
            <shiness>5.000000</shiness>
            <ambient>
                <r>0.500000</r>
                <g>0.500000</g>
                <b>0.500000</b>
            </ambient>
            <sphereMode>None</sphereMode>
            <toonID>0</toonID>
            <edgeColor>
                <r>0.000000</r>
                <g>0.000000</g>
                <b>0.000000</b>
                <a>1.000000</a>
            </edgeColor>
            <edgeSize>2.000000</edgeSize>
            <textureID>26</textureID>
            <additionalTextureID>-1</additionalTextureID>
            <toonTextureID>9</toonTextureID>
            <flags>12</flags>
            <isDrawBothFaces>0</isDrawBothFaces>
            <isDrawGroundShadow>0</isDrawGroundShadow>
            <isDrawSelfShadowMap>1</isDrawSelfShadowMap>
            <isDrawSelfShadow>1</isDrawSelfShadow>
            <isDrawEdge>0</isDrawEdge>
            <numIndex>2130</numIndex>
        </Material>
        <Material>
            <nameJp>壁Ｂ</nameJp>
            <nameEn></nameEn>
            <materialName>29.kabeB</materialName>
            <translatedName>kabeB</translatedName>
            <surfaceName>29.kabeB</surfaceName>
            <diffuse>
                <r>0.900000</r>
                <g>0.900000</g>
                <b>0.900000</b>
                <a>1.000000</a>
            </diffuse>
            <specular>
                <r>0.050000</r>
                <g>0.050000</g>
                <b>0.050000</b>
            </specular>
            <shiness>5.000000</shiness>
            <ambient>
                <r>0.500000</r>
                <g>0.500000</g>
                <b>0.500000</b>
            </ambient>
            <sphereMode>None</sphereMode>
            <toonID>0</toonID>
            <edgeColor>
                <r>0.000000</r>
                <g>0.000000</g>
                <b>0.000000</b>
                <a>1.000000</a>
            </edgeColor>
            <edgeSize>2.000000</edgeSize>
            <textureID>26</textureID>
            <additionalTextureID>-1</additionalTextureID>
            <toonTextureID>9</toonTextureID>
            <flags>12</flags>
            <isDrawBothFaces>0</isDrawBothFaces>
            <isDrawGroundShadow>0</isDrawGroundShadow>
            <isDrawSelfShadowMap>1</isDrawSelfShadowMap>
            <isDrawSelfShadow>1</isDrawSelfShadow>
            <isDrawEdge>0</isDrawEdge>
            <numIndex>8547</numIndex>
        </Material>
        <Material>
            <nameJp>壁Ｃ</nameJp>
            <nameEn></nameEn>
            <materialName>30.kabeC</materialName>
            <translatedName>kabeC</translatedName>
            <surfaceName>30.kabeC</surfaceName>
            <diffuse>
                <r>0.900000</r>
                <g>0.900000</g>
                <b>0.900000</b>
                <a>1.000000</a>
            </diffuse>
            <specular>
                <r>0.050000</r>
                <g>0.050000</g>
                <b>0.050000</b>
            </specular>
            <shiness>5.000000</shiness>
            <ambient>
                <r>0.500000</r>
                <g>0.500000</g>
                <b>0.500000</b>
            </ambient>
            <sphereMode>None</sphereMode>
            <toonID>0</toonID>
            <edgeColor>
                <r>0.000000</r>
                <g>0.000000</g>
                <b>0.000000</b>
                <a>1.000000</a>
            </edgeColor>
            <edgeSize>2.000000</edgeSize>
            <textureID>27</textureID>
            <additionalTextureID>-1</additionalTextureID>
            <toonTextureID>9</toonTextureID>
            <flags>12</flags>
            <isDrawBothFaces>0</isDrawBothFaces>
            <isDrawGroundShadow>0</isDrawGroundShadow>
            <isDrawSelfShadowMap>1</isDrawSelfShadowMap>
            <isDrawSelfShadow>1</isDrawSelfShadow>
            <isDrawEdge>0</isDrawEdge>
            <numIndex>37242</numIndex>
        </Material>
        <Material>
            <nameJp>壁Ｃ2</nameJp>
            <nameEn></nameEn>
            <materialName>31.kabeC2</materialName>
            <translatedName>kabeC2</translatedName>
            <surfaceName>31.kabeC2</surfaceName>
            <diffuse>
                <r>0.900000</r>
                <g>0.900000</g>
                <b>0.900000</b>
                <a>1.000000</a>
            </diffuse>
            <specular>
                <r>0.050000</r>
                <g>0.050000</g>
                <b>0.050000</b>
            </specular>
            <shiness>5.000000</shiness>
            <ambient>
                <r>0.500000</r>
                <g>0.500000</g>
                <b>0.500000</b>
            </ambient>
            <sphereMode>None</sphereMode>
            <toonID>1</toonID>
            <edgeColor>
                <r>0.000000</r>
                <g>0.000000</g>
                <b>0.000000</b>
                <a>1.000000</a>
            </edgeColor>
            <edgeSize>2.000000</edgeSize>
            <textureID>28</textureID>
            <additionalTextureID>-1</additionalTextureID>
            <toonTextureID>-1</toonTextureID>
            <flags>12</flags>
            <isDrawBothFaces>0</isDrawBothFaces>
            <isDrawGroundShadow>0</isDrawGroundShadow>
            <isDrawSelfShadowMap>1</isDrawSelfShadowMap>
            <isDrawSelfShadow>1</isDrawSelfShadow>
            <isDrawEdge>0</isDrawEdge>
            <numIndex>516</numIndex>
        </Material>
        <Material>
            <nameJp>壁Ｄ</nameJp>
            <nameEn></nameEn>
            <materialName>32.kabeE</materialName>
            <translatedName>kabeE</translatedName>
            <surfaceName>32.kabeE</surfaceName>
            <diffuse>
                <r>0.900000</r>
                <g>0.900000</g>
                <b>0.900000</b>
                <a>1.000000</a>
            </diffuse>
            <specular>
                <r>0.050000</r>
                <g>0.050000</g>
                <b>0.050000</b>
            </specular>
            <shiness>5.000000</shiness>
            <ambient>
                <r>0.500000</r>
                <g>0.500000</g>
                <b>0.500000</b>
            </ambient>
            <sphereMode>None</sphereMode>
            <toonID>1</toonID>
            <edgeColor>
                <r>0.000000</r>
                <g>0.000000</g>
                <b>0.000000</b>
                <a>1.000000</a>
            </edgeColor>
            <edgeSize>2.000000</edgeSize>
            <textureID>29</textureID>
            <additionalTextureID>-1</additionalTextureID>
            <toonTextureID>-1</toonTextureID>
            <flags>12</flags>
            <isDrawBothFaces>0</isDrawBothFaces>
            <isDrawGroundShadow>0</isDrawGroundShadow>
            <isDrawSelfShadowMap>1</isDrawSelfShadowMap>
            <isDrawSelfShadow>1</isDrawSelfShadow>
            <isDrawEdge>0</isDrawEdge>
            <numIndex>15444</numIndex>
        </Material>
        <Material>
            <nameJp>金属</nameJp>
            <nameEn></nameEn>
            <materialName>33.kinzoku</materialName>
            <translatedName>kinzoku</translatedName>
            <surfaceName>33.kinzoku</surfaceName>
            <diffuse>
                <r>0.874510</r>
                <g>0.874510</g>
                <b>0.874510</b>
                <a>1.000000</a>
            </diffuse>
            <specular>
                <r>0.500000</r>
                <g>0.500000</g>
                <b>0.500000</b>
            </specular>
            <shiness>6.000000</shiness>
            <ambient>
                <r>0.439216</r>
                <g>0.439216</g>
                <b>0.439216</b>
            </ambient>
            <sphereMode>Multiply</sphereMode>
            <toonID>1</toonID>
            <edgeColor>
                <r>0.000000</r>
                <g>0.000000</g>
                <b>0.000000</b>
                <a>1.000000</a>
            </edgeColor>
            <edgeSize>2.000000</edgeSize>
            <textureID>-1</textureID>
            <additionalTextureID>30</additionalTextureID>
            <toonTextureID>-1</toonTextureID>
            <flags>12</flags>
            <isDrawBothFaces>0</isDrawBothFaces>
            <isDrawGroundShadow>0</isDrawGroundShadow>
            <isDrawSelfShadowMap>1</isDrawSelfShadowMap>
            <isDrawSelfShadow>1</isDrawSelfShadow>
            <isDrawEdge>0</isDrawEdge>
            <numIndex>2088</numIndex>
        </Material>
        <Material>
            <nameJp>建物遠景</nameJp>
            <nameEn></nameEn>
            <materialName>34.tatemonoenkei</materialName>
            <translatedName>tatemonoenkei</translatedName>
            <surfaceName>34.tatemonoenkei</surfaceName>
            <diffuse>
                <r>0.900000</r>
                <g>0.900000</g>
                <b>0.900000</b>
                <a>1.000000</a>
            </diffuse>
            <specular>
                <r>0.050000</r>
                <g>0.050000</g>
                <b>0.050000</b>
            </specular>
            <shiness>5.000000</shiness>
            <ambient>
                <r>0.500000</r>
                <g>0.500000</g>
                <b>0.500000</b>
            </ambient>
            <sphereMode>None</sphereMode>
            <toonID>1</toonID>
            <edgeColor>
                <r>0.000000</r>
                <g>0.000000</g>
                <b>0.000000</b>
                <a>1.000000</a>
            </edgeColor>
            <edgeSize>2.000000</edgeSize>
            <textureID>31</textureID>
            <additionalTextureID>-1</additionalTextureID>
            <toonTextureID>-1</toonTextureID>
            <flags>12</flags>
            <isDrawBothFaces>0</isDrawBothFaces>
            <isDrawGroundShadow>0</isDrawGroundShadow>
            <isDrawSelfShadowMap>1</isDrawSelfShadowMap>
            <isDrawSelfShadow>1</isDrawSelfShadow>
            <isDrawEdge>0</isDrawEdge>
            <numIndex>264</numIndex>
        </Material>
        <Material>
            <nameJp>黒鉄</nameJp>
            <nameEn></nameEn>
            <materialName>35.kurotetsu</materialName>
            <translatedName>kurotetsu</translatedName>
            <surfaceName>35.kurotetsu</surfaceName>
            <diffuse>
                <r>0.233100</r>
                <g>0.169200</g>
                <b>0.169200</b>
                <a>1.000000</a>
            </diffuse>
            <specular>
                <r>0.050000</r>
                <g>0.050000</g>
                <b>0.050000</b>
            </specular>
            <shiness>5.000000</shiness>
            <ambient>
                <r>0.129500</r>
                <g>0.094000</g>
                <b>0.094000</b>
            </ambient>
            <sphereMode>None</sphereMode>
            <toonID>0</toonID>
            <edgeColor>
                <r>0.000000</r>
                <g>0.000000</g>
                <b>0.000000</b>
                <a>1.000000</a>
            </edgeColor>
            <edgeSize>2.000000</edgeSize>
            <textureID>32</textureID>
            <additionalTextureID>-1</additionalTextureID>
            <toonTextureID>9</toonTextureID>
            <flags>12</flags>
            <isDrawBothFaces>0</isDrawBothFaces>
            <isDrawGroundShadow>0</isDrawGroundShadow>
            <isDrawSelfShadowMap>1</isDrawSelfShadowMap>
            <isDrawSelfShadow>1</isDrawSelfShadow>
            <isDrawEdge>0</isDrawEdge>
            <numIndex>17040</numIndex>
        </Material>
        <Material>
            <nameJp>ステップ</nameJp>
            <nameEn></nameEn>
            <materialName>36.sutetsu_</materialName>
            <translatedName>sutetsu_</translatedName>
            <surfaceName>36.sutetsu_</surfaceName>
            <diffuse>
                <r>0.380000</r>
                <g>0.278000</g>
                <b>0.255000</b>
                <a>1.000000</a>
            </diffuse>
            <specular>
                <r>0.100000</r>
                <g>0.100000</g>
                <b>0.100000</b>
            </specular>
            <shiness>6.000000</shiness>
            <ambient>
                <r>0.190000</r>
                <g>0.139000</g>
                <b>0.127500</b>
            </ambient>
            <sphereMode>None</sphereMode>
            <toonID>1</toonID>
            <edgeColor>
                <r>0.000000</r>
                <g>0.000000</g>
                <b>0.000000</b>
                <a>1.000000</a>
            </edgeColor>
            <edgeSize>2.000000</edgeSize>
            <textureID>33</textureID>
            <additionalTextureID>-1</additionalTextureID>
            <toonTextureID>-1</toonTextureID>
            <flags>12</flags>
            <isDrawBothFaces>0</isDrawBothFaces>
            <isDrawGroundShadow>0</isDrawGroundShadow>
            <isDrawSelfShadowMap>1</isDrawSelfShadowMap>
            <isDrawSelfShadow>1</isDrawSelfShadow>
            <isDrawEdge>0</isDrawEdge>
            <numIndex>108</numIndex>
        </Material>
        <Material>
            <nameJp>鉄骨</nameJp>
            <nameEn></nameEn>
            <materialName>37.tekkotsu</materialName>
            <translatedName>tekkotsu</translatedName>
            <surfaceName>37.tekkotsu</surfaceName>
            <diffuse>
                <r>0.270588</r>
                <g>0.270588</g>
                <b>0.270588</b>
                <a>1.000000</a>
            </diffuse>
            <specular>
                <r>0.000000</r>
                <g>0.000000</g>
                <b>0.000000</b>
            </specular>
            <shiness>6.000000</shiness>
            <ambient>
                <r>0.016500</r>
                <g>0.016500</g>
                <b>0.016500</b>
            </ambient>
            <sphereMode>Multiply</sphereMode>
            <toonID>1</toonID>
            <edgeColor>
                <r>0.000000</r>
                <g>0.000000</g>
                <b>0.000000</b>
                <a>1.000000</a>
            </edgeColor>
            <edgeSize>2.000000</edgeSize>
            <textureID>-1</textureID>
            <additionalTextureID>30</additionalTextureID>
            <toonTextureID>-1</toonTextureID>
            <flags>12</flags>
            <isDrawBothFaces>0</isDrawBothFaces>
            <isDrawGroundShadow>0</isDrawGroundShadow>
            <isDrawSelfShadowMap>1</isDrawSelfShadowMap>
            <isDrawSelfShadow>1</isDrawSelfShadow>
            <isDrawEdge>0</isDrawEdge>
            <numIndex>168</numIndex>
        </Material>
        <Material>
            <nameJp>アーチ天井</nameJp>
            <nameEn></nameEn>
            <materialName>38.a^chitenjou</materialName>
            <translatedName>a^chitenjou</translatedName>
            <surfaceName>38.a^chitenjou</surfaceName>
            <diffuse>
                <r>0.900000</r>
                <g>0.900000</g>
                <b>0.900000</b>
                <a>1.000000</a>
            </diffuse>
            <specular>
                <r>0.000000</r>
                <g>0.000000</g>
                <b>0.000000</b>
            </specular>
            <shiness>6.000000</shiness>
            <ambient>
                <r>0.500000</r>
                <g>0.500000</g>
                <b>0.500000</b>
            </ambient>
            <sphereMode>None</sphereMode>
            <toonID>0</toonID>
            <edgeColor>
                <r>0.000000</r>
                <g>0.000000</g>
                <b>0.000000</b>
                <a>1.000000</a>
            </edgeColor>
            <edgeSize>2.000000</edgeSize>
            <textureID>34</textureID>
            <additionalTextureID>-1</additionalTextureID>
            <toonTextureID>9</toonTextureID>
            <flags>8</flags>
            <isDrawBothFaces>0</isDrawBothFaces>
            <isDrawGroundShadow>0</isDrawGroundShadow>
            <isDrawSelfShadowMap>0</isDrawSelfShadowMap>
            <isDrawSelfShadow>1</isDrawSelfShadow>
            <isDrawEdge>0</isDrawEdge>
            <numIndex>18018</numIndex>
        </Material>
        <Material>
            <nameJp>吊り下げ照明</nameJp>
            <nameEn></nameEn>
            <materialName>39.tsurisageshoumei</materialName>
            <translatedName>tsurisageshoumei</translatedName>
            <surfaceName>39.tsurisageshoumei</surfaceName>
            <diffuse>
                <r>1.000000</r>
                <g>1.000000</g>
                <b>1.000000</b>
                <a>1.000000</a>
            </diffuse>
            <specular>
                <r>0.000000</r>
                <g>0.000000</g>
                <b>0.000000</b>
            </specular>
            <shiness>110.000000</shiness>
            <ambient>
                <r>0.500000</r>
                <g>0.500000</g>
                <b>0.500000</b>
            </ambient>
            <sphereMode>None</sphereMode>
            <toonID>0</toonID>
            <edgeColor>
                <r>0.000000</r>
                <g>0.000000</g>
                <b>0.000000</b>
                <a>1.000000</a>
            </edgeColor>
            <edgeSize>2.000000</edgeSize>
            <textureID>35</textureID>
            <additionalTextureID>-1</additionalTextureID>
            <toonTextureID>9</toonTextureID>
            <flags>8</flags>
            <isDrawBothFaces>0</isDrawBothFaces>
            <isDrawGroundShadow>0</isDrawGroundShadow>
            <isDrawSelfShadowMap>0</isDrawSelfShadowMap>
            <isDrawSelfShadow>1</isDrawSelfShadow>
            <isDrawEdge>0</isDrawEdge>
            <numIndex>7224</numIndex>
        </Material>
        <Material>
            <nameJp>鉄板</nameJp>
            <nameEn></nameEn>
            <materialName>40.tetsu_n</materialName>
            <translatedName>tetsu_n</translatedName>
            <surfaceName>40.tetsu_n</surfaceName>
            <diffuse>
                <r>0.402300</r>
                <g>0.292500</g>
                <b>0.292500</b>
                <a>1.000000</a>
            </diffuse>
            <specular>
                <r>0.050000</r>
                <g>0.050000</g>
                <b>0.050000</b>
            </specular>
            <shiness>5.000000</shiness>
            <ambient>
                <r>0.223500</r>
                <g>0.162500</g>
                <b>0.162500</b>
            </ambient>
            <sphereMode>None</sphereMode>
            <toonID>1</toonID>
            <edgeColor>
                <r>0.000000</r>
                <g>0.000000</g>
                <b>0.000000</b>
                <a>1.000000</a>
            </edgeColor>
            <edgeSize>2.000000</edgeSize>
            <textureID>32</textureID>
            <additionalTextureID>-1</additionalTextureID>
            <toonTextureID>-1</toonTextureID>
            <flags>12</flags>
            <isDrawBothFaces>0</isDrawBothFaces>
            <isDrawGroundShadow>0</isDrawGroundShadow>
            <isDrawSelfShadowMap>1</isDrawSelfShadowMap>
            <isDrawSelfShadow>1</isDrawSelfShadow>
            <isDrawEdge>0</isDrawEdge>
            <numIndex>84</numIndex>
        </Material>
        <Material>
            <nameJp>金メッキ</nameJp>
            <nameEn></nameEn>
            <materialName>41.kinmekki</materialName>
            <translatedName>kinmekki</translatedName>
            <surfaceName>41.kinmekki</surfaceName>
            <diffuse>
                <r>1.000000</r>
                <g>0.886275</g>
                <b>0.501961</b>
                <a>1.000000</a>
            </diffuse>
            <specular>
                <r>0.500000</r>
                <g>0.500000</g>
                <b>0.500000</b>
            </specular>
            <shiness>6.000000</shiness>
            <ambient>
                <r>0.807843</r>
                <g>0.623529</g>
                <b>0.000000</b>
            </ambient>
            <sphereMode>Multiply</sphereMode>
            <toonID>0</toonID>
            <edgeColor>
                <r>0.000000</r>
                <g>0.000000</g>
                <b>0.000000</b>
                <a>1.000000</a>
            </edgeColor>
            <edgeSize>2.000000</edgeSize>
            <textureID>-1</textureID>
            <additionalTextureID>30</additionalTextureID>
            <toonTextureID>9</toonTextureID>
            <flags>12</flags>
            <isDrawBothFaces>0</isDrawBothFaces>
            <isDrawGroundShadow>0</isDrawGroundShadow>
            <isDrawSelfShadowMap>1</isDrawSelfShadowMap>
            <isDrawSelfShadow>1</isDrawSelfShadow>
            <isDrawEdge>0</isDrawEdge>
            <numIndex>648</numIndex>
        </Material>
        <Material>
            <nameJp>鉄骨緑</nameJp>
            <nameEn></nameEn>
            <materialName>42.tekkotsumidori</materialName>
            <translatedName>tekkotsumidori</translatedName>
            <surfaceName>42.tekkotsumidori</surfaceName>
            <diffuse>
                <r>0.900000</r>
                <g>0.900000</g>
                <b>0.900000</b>
                <a>1.000000</a>
            </diffuse>
            <specular>
                <r>0.050000</r>
                <g>0.050000</g>
                <b>0.050000</b>
            </specular>
            <shiness>5.000000</shiness>
            <ambient>
                <r>0.500000</r>
                <g>0.500000</g>
                <b>0.500000</b>
            </ambient>
            <sphereMode>Multiply</sphereMode>
            <toonID>0</toonID>
            <edgeColor>
                <r>0.000000</r>
                <g>0.000000</g>
                <b>0.000000</b>
                <a>1.000000</a>
            </edgeColor>
            <edgeSize>2.000000</edgeSize>
            <textureID>32</textureID>
            <additionalTextureID>30</additionalTextureID>
            <toonTextureID>9</toonTextureID>
            <flags>12</flags>
            <isDrawBothFaces>0</isDrawBothFaces>
            <isDrawGroundShadow>0</isDrawGroundShadow>
            <isDrawSelfShadowMap>1</isDrawSelfShadowMap>
            <isDrawSelfShadow>1</isDrawSelfShadow>
            <isDrawEdge>0</isDrawEdge>
            <numIndex>9951</numIndex>
        </Material>
        <Material>
            <nameJp>ベンチ</nameJp>
            <nameEn></nameEn>
            <materialName>43.benchi</materialName>
            <translatedName>benchi</translatedName>
            <surfaceName>43.benchi</surfaceName>
            <diffuse>
                <r>0.380000</r>
                <g>0.278000</g>
                <b>0.255000</b>
                <a>1.000000</a>
            </diffuse>
            <specular>
                <r>0.100000</r>
                <g>0.100000</g>
                <b>0.100000</b>
            </specular>
            <shiness>6.000000</shiness>
            <ambient>
                <r>0.190000</r>
                <g>0.139000</g>
                <b>0.127500</b>
            </ambient>
            <sphereMode>Adding</sphereMode>
            <toonID>0</toonID>
            <edgeColor>
                <r>0.000000</r>
                <g>0.000000</g>
                <b>0.000000</b>
                <a>1.000000</a>
            </edgeColor>
            <edgeSize>2.000000</edgeSize>
            <textureID>33</textureID>
            <additionalTextureID>36</additionalTextureID>
            <toonTextureID>9</toonTextureID>
            <flags>12</flags>
            <isDrawBothFaces>0</isDrawBothFaces>
            <isDrawGroundShadow>0</isDrawGroundShadow>
            <isDrawSelfShadowMap>1</isDrawSelfShadowMap>
            <isDrawSelfShadow>1</isDrawSelfShadow>
            <isDrawEdge>0</isDrawEdge>
            <numIndex>2184</numIndex>
        </Material>
        <Material>
            <nameJp>街灯</nameJp>
            <nameEn></nameEn>
            <materialName>44.gaitou</materialName>
            <translatedName>gaitou</translatedName>
            <surfaceName>44.gaitou</surfaceName>
            <diffuse>
                <r>0.900000</r>
                <g>0.900000</g>
                <b>0.900000</b>
                <a>1.000000</a>
            </diffuse>
            <specular>
                <r>0.050000</r>
                <g>0.050000</g>
                <b>0.050000</b>
            </specular>
            <shiness>5.000000</shiness>
            <ambient>
                <r>0.500000</r>
                <g>0.500000</g>
                <b>0.500000</b>
            </ambient>
            <sphereMode>Adding</sphereMode>
            <toonID>0</toonID>
            <edgeColor>
                <r>0.000000</r>
                <g>0.000000</g>
                <b>0.000000</b>
                <a>1.000000</a>
            </edgeColor>
            <edgeSize>2.000000</edgeSize>
            <textureID>32</textureID>
            <additionalTextureID>36</additionalTextureID>
            <toonTextureID>9</toonTextureID>
            <flags>12</flags>
            <isDrawBothFaces>0</isDrawBothFaces>
            <isDrawGroundShadow>0</isDrawGroundShadow>
            <isDrawSelfShadowMap>1</isDrawSelfShadowMap>
            <isDrawSelfShadow>1</isDrawSelfShadow>
            <isDrawEdge>0</isDrawEdge>
            <numIndex>48852</numIndex>
        </Material>
        <Material>
            <nameJp>kuro</nameJp>
            <nameEn></nameEn>
            <materialName>45.kuro</materialName>
            <translatedName>kuro</translatedName>
            <surfaceName>45.kuro</surfaceName>
            <diffuse>
                <r>1.000000</r>
                <g>1.000000</g>
                <b>1.000000</b>
                <a>0.990000</a>
            </diffuse>
            <specular>
                <r>0.060000</r>
                <g>0.060000</g>
                <b>0.060000</b>
            </specular>
            <shiness>6.000000</shiness>
            <ambient>
                <r>0.500000</r>
                <g>0.500000</g>
                <b>0.500000</b>
            </ambient>
            <sphereMode>None</sphereMode>
            <toonID>1</toonID>
            <edgeColor>
                <r>0.000000</r>
                <g>0.000000</g>
                <b>0.000000</b>
                <a>1.000000</a>
            </edgeColor>
            <edgeSize>2.000000</edgeSize>
            <textureID>37</textureID>
            <additionalTextureID>-1</additionalTextureID>
            <toonTextureID>-1</toonTextureID>
            <flags>12</flags>
            <isDrawBothFaces>0</isDrawBothFaces>
            <isDrawGroundShadow>0</isDrawGroundShadow>
            <isDrawSelfShadowMap>1</isDrawSelfShadowMap>
            <isDrawSelfShadow>1</isDrawSelfShadow>
            <isDrawEdge>0</isDrawEdge>
            <numIndex>216</numIndex>
        </Material>
        <Material>
            <nameJp>ベランダ</nameJp>
            <nameEn></nameEn>
            <materialName>46.beranda</materialName>
            <translatedName>beranda</translatedName>
            <surfaceName>46.beranda</surfaceName>
            <diffuse>
                <r>0.900000</r>
                <g>0.900000</g>
                <b>0.900000</b>
                <a>0.990000</a>
            </diffuse>
            <specular>
                <r>0.060000</r>
                <g>0.060000</g>
                <b>0.060000</b>
            </specular>
            <shiness>6.000000</shiness>
            <ambient>
                <r>0.500000</r>
                <g>0.500000</g>
                <b>0.500000</b>
            </ambient>
            <sphereMode>None</sphereMode>
            <toonID>1</toonID>
            <edgeColor>
                <r>0.000000</r>
                <g>0.000000</g>
                <b>0.000000</b>
                <a>1.000000</a>
            </edgeColor>
            <edgeSize>2.000000</edgeSize>
            <textureID>37</textureID>
            <additionalTextureID>-1</additionalTextureID>
            <toonTextureID>-1</toonTextureID>
            <flags>8</flags>
            <isDrawBothFaces>0</isDrawBothFaces>
            <isDrawGroundShadow>0</isDrawGroundShadow>
            <isDrawSelfShadowMap>0</isDrawSelfShadowMap>
            <isDrawSelfShadow>1</isDrawSelfShadow>
            <isDrawEdge>0</isDrawEdge>
            <numIndex>20580</numIndex>
        </Material>
        <Material>
            <nameJp>手すり</nameJp>
            <nameEn></nameEn>
            <materialName>47.tesuri</materialName>
            <translatedName>tesuri</translatedName>
            <surfaceName>47.tesuri</surfaceName>
            <diffuse>
                <r>0.900000</r>
                <g>0.900000</g>
                <b>0.900000</b>
                <a>0.990000</a>
            </diffuse>
            <specular>
                <r>0.050000</r>
                <g>0.050000</g>
                <b>0.050000</b>
            </specular>
            <shiness>5.000000</shiness>
            <ambient>
                <r>0.500000</r>
                <g>0.500000</g>
                <b>0.500000</b>
            </ambient>
            <sphereMode>None</sphereMode>
            <toonID>1</toonID>
            <edgeColor>
                <r>0.000000</r>
                <g>0.000000</g>
                <b>0.000000</b>
                <a>1.000000</a>
            </edgeColor>
            <edgeSize>2.000000</edgeSize>
            <textureID>38</textureID>
            <additionalTextureID>-1</additionalTextureID>
            <toonTextureID>-1</toonTextureID>
            <flags>8</flags>
            <isDrawBothFaces>0</isDrawBothFaces>
            <isDrawGroundShadow>0</isDrawGroundShadow>
            <isDrawSelfShadowMap>0</isDrawSelfShadowMap>
            <isDrawSelfShadow>1</isDrawSelfShadow>
            <isDrawEdge>0</isDrawEdge>
            <numIndex>576</numIndex>
        </Material>
        <Material>
            <nameJp>ガラス</nameJp>
            <nameEn></nameEn>
            <materialName>48.garasu</materialName>
            <translatedName>garasu</translatedName>
            <surfaceName>48.garasu</surfaceName>
            <diffuse>
                <r>0.714000</r>
                <g>0.545000</g>
                <b>0.408000</b>
                <a>0.300000</a>
            </diffuse>
            <specular>
                <r>0.000000</r>
                <g>0.000000</g>
                <b>0.000000</b>
            </specular>
            <shiness>102.000000</shiness>
            <ambient>
                <r>0.714000</r>
                <g>0.545000</g>
                <b>0.408000</b>
            </ambient>
            <sphereMode>Multiply</sphereMode>
            <toonID>0</toonID>
            <edgeColor>
                <r>0.000000</r>
                <g>0.000000</g>
                <b>0.000000</b>
                <a>1.000000</a>
            </edgeColor>
            <edgeSize>2.000000</edgeSize>
            <textureID>-1</textureID>
            <additionalTextureID>-1</additionalTextureID>
            <toonTextureID>9</toonTextureID>
            <flags>12</flags>
            <isDrawBothFaces>0</isDrawBothFaces>
            <isDrawGroundShadow>0</isDrawGroundShadow>
            <isDrawSelfShadowMap>1</isDrawSelfShadowMap>
            <isDrawSelfShadow>1</isDrawSelfShadow>
            <isDrawEdge>0</isDrawEdge>
            <numIndex>7464</numIndex>
        </Material>
    </materialList>
    <boneList>
        <Bone>
            <nameJp>センター</nameJp>
            <nameEn>center</nameEn>
            <skeletonName>0.joint_Center</skeletonName>
            <parentBoneID>1</parentBoneID>
            <sortedBoneID>1</sortedBoneID>
            <originalParentBoneID>-1</originalParentBoneID>
            <originalSortedBoneID>0</originalSortedBoneID>
            <origin>
                <x>0.000000</x>
                <y>0.000000</y>
                <z>0.000000</z>
            </origin>
            <additionalFlags>0</additionalFlags>
            <isLimitAngleX>0</isLimitAngleX>
            <transformLayerID>0</transformLayerID>
            <flags>30</flags>
            <destination>0</destination>
            <isRotate>1</isRotate>
            <isTranslate>1</isTranslate>
            <isVisible>1</isVisible>
            <isControllable>1</isControllable>
            <isIK>0</isIK>
            <inherenceLocal>0</inherenceLocal>
            <isInherenceRotate>0</isInherenceRotate>
            <isInherenceTranslate>0</isInherenceTranslate>
            <isFixedAxis>0</isFixedAxis>
            <isLocalAxis>0</isLocalAxis>
            <isTransformAfterPhysics>0</isTransformAfterPhysics>
            <isTransformExternalParent>0</isTransformExternalParent>
            <destinationOrigin>
                <x>0.000000</x>
                <y>0.000000</y>
                <z>0.000000</z>
            </destinationOrigin>
        </Bone>
        <Bone>
            <additionalFlags>2147483648</additionalFlags>
            <nameJp>ルート</nameJp>
            <nameEn>Root</nameEn>
            <skeletonName>1.!Root</skeletonName>
            <parentBoneID>-1</parentBoneID>
            <sortedBoneID>0</sortedBoneID>
            <originalParentBoneID>-1</originalParentBoneID>
            <originalSortedBoneID>-1</originalSortedBoneID>
        </Bone>
    </boneList>
    <ikList />
    <morphList />
    <displayFrameList>
        <DisplayFrame>
            <nameJp>Root</nameJp>
            <nameEn>Root</nameEn>
            <additionalFlags>1</additionalFlags>
            <isSpecial>1</isSpecial>
            <itemList>
                <Item>
                    <type>Bone</type>
                    <index>0</index>
                </Item>
            </itemList>
        </DisplayFrame>
        <DisplayFrame>
            <nameJp>表情</nameJp>
            <nameEn>Exp</nameEn>
            <additionalFlags>1</additionalFlags>
            <isSpecial>1</isSpecial>
            <itemList />
        </DisplayFrame>
    </displayFrameList>
    <rigidBodyList />
    <jointList />
</MMDModel>
